blacknet/__init__.py
blacknet/client.py
blacknet/common.py
blacknet/config.py
blacknet/database.py
blacknet/logger.py
blacknet/master.py
blacknet/py.typed
blacknet/scrubber.py
blacknet/sensor.py
blacknet/server.py
blacknet/sslif.py
blacknet/updater.py
blacknet/version.py
blacknet/console/__init__.py
blacknet/console/master.py
blacknet/console/scrubber.py
blacknet/console/sensor.py
blacknet/console/updater.py
blacknet-2.1.0.dist-info/LICENSE
blacknet-2.1.0.dist-info/METADATA
blacknet-2.1.0.dist-info/WHEEL
blacknet-2.1.0.dist-info/entry_points.txt
blacknet-2.1.0.dist-info/top_level.txt
blacknet-2.1.0.dist-info/RECORD
