Metadata-Version: 2.1
Name: blacknet
Version: 2.1.0
Summary: Multi-head SSH honeypot system
Author-email: Romain Bezut <blacknet@xdec.net>
Classifier: License :: OSI Approved :: MIT License
Classifier: Operating System :: POSIX :: Linux
Classifier: Programming Language :: Python
Classifier: Programming Language :: Python :: 3
Classifier: Programming Language :: Python :: 3 :: Only
Classifier: Programming Language :: Python :: 3.9
Classifier: Programming Language :: Python :: 3.10
Classifier: Programming Language :: Python :: 3.11
License-File: LICENSE
Requires-Dist: msgpack >=1.0.0
Requires-Dist: PyMySQL
Requires-Dist: paramiko
